pyuarm
