Metadata-Version: 1.0
Name: pyuarm
Version: 2.2.5.2
Summary: A python library for uArm
Home-page: https://github.com/uarm-developer/pyuarm
Author: Alex Tan
Author-email: developer@ufactory.cc
License: MIT
Keywords: pyuarm uarm4py uarmForPython uarm ufactory
Platform: UNKNOWN
